vgc_zero_lcd/__init__.py
vgc_zero_lcd/config.py
vgc_zero_lcd/lcd.py
vgc_zero_lcd/test.py
vgc_zero_lcd/vgc.py
vgc_zero_lcd-1.0.0.dist-info/LICENSE
vgc_zero_lcd-1.0.0.dist-info/METADATA
vgc_zero_lcd-1.0.0.dist-info/WHEEL
vgc_zero_lcd-1.0.0.dist-info/top_level.txt
vgc_zero_lcd-1.0.0.dist-info/RECORD
